{
    "required": true,
    "minVersion": "0.7.10",
    "package": "de.scribble.lp.tasmod.mixin",
    "refmap": "mixins.tasmod.refmap.json",
    "compatibilityLevel": "JAVA_8",
    "mixins": [
        "MixinMinecraftServer",
        "savestates.MixinChunkProviderServer",
        "savestates.MixinEntityPlayerMP",
        "MixinDragonFightManager",
        "killtherng.MixinUUIDFix",
        "killtherng.redirect.RedirectBlockCrops",
    	"killtherng.redirect.RedirectBlockDispenser",
    	"killtherng.redirect.RedirectBlockLeaves",
    	"killtherng.redirect.RedirectBlockNetherWart",
    	"killtherng.redirect.RedirectBlockOre",
    	"killtherng.redirect.RedirectCommandSpreadPlayers",
    	"killtherng.redirect.RedirectCommandWeather",
    	"killtherng.redirect.RedirectContainerEnchantment",
    	"killtherng.redirect.RedirectEntityRandom",
    	"killtherng.redirect.RedirectEntityMinecartContainer",
    	"killtherng.redirect.RedirectEntityLivingRandom",
    	"killtherng.redirect.RedirectTeleportToTeam",
    	"killtherng.redirect.RedirectTileEntityLockableLoot",
    	"killtherng.redirect.RedirectDragonFightManager",
    	"killtherng.redirect.RedirectMapGenStronghold",
    	"killtherng.redirect.RedirectMapGenStructure",
    	"killtherng.redirect.RedirectExplosion",
    	"killtherng.redirect.RedirectWorld",
    	"killtherng.redirect.RedirectDragonSpawnManager"
    ],
    "client": [
        "MixinMinecraft2",
        "MixinEntityRenderer",
        "MixinGuiScreen2",
		"savestates.MixinChunkProviderClient",
		"MixinFrustum",
		"MixinTextfield",
		"MixinNetHandlerPlayClient",
		"MixinWOrldClient",
		"killtherng.MixinMainMenu",
		"killtherng.MixinMinecraft"
	]
}